dav2rem.py
rem2dav.py
remind_caldav-0.8.0.dist-info/LICENSE
remind_caldav-0.8.0.dist-info/METADATA
remind_caldav-0.8.0.dist-info/WHEEL
remind_caldav-0.8.0.dist-info/entry_points.txt
remind_caldav-0.8.0.dist-info/top_level.txt
remind_caldav-0.8.0.dist-info/RECORD
