Metadata-Version: 2.1
Name: remind-caldav
Version: 0.8.0
Summary: Remind CalDAV tools
Home-page: https://github.com/jspricke/remind-caldav
Author: Jochen Sprickerhof
Author-email: remind@jochen.sprickerhof.de
License: GPLv3+
Keywords: Remind
Platform: UNKNOWN
Classifier: Programming Language :: Python
Classifier: Development Status :: 4 - Beta
Classifier: Environment :: Console
Classifier: License :: OSI Approved :: GNU General Public License v3 or later (GPLv3+)
Classifier: Topic :: Office/Business :: Scheduling
License-File: LICENSE
Requires-Dist: caldav
Requires-Dist: python-dateutil
Requires-Dist: remind
Requires-Dist: vobject
